README.rst
setup.cfg
setup.py
vecpy/__init__.py
vecpy/vecpy.py
vecpy.egg-info/PKG-INFO
vecpy.egg-info/SOURCES.txt
vecpy.egg-info/dependency_links.txt
vecpy.egg-info/not-zip-safe
vecpy.egg-info/top_level.txt