Metadata-Version: 1.1
Name: vecpy
Version: 0.1.1
Summary: Simple Vector package to help with basic linear algebra.
Home-page: https://github.com/j-i-l/VecPy
Author: Jonas I. Liechti
Author-email: jon.liechti@gmail.com
License: Apache 2.0
Download-URL: https://github.com/j-i-l/VecPy/tarball/0.1.0
Keywords: vector,linear algebra,projection
Platform: UNKNOWN
Classifier: Development Status :: 3 - Alpha
Classifier: Intended Audience :: Developers
Classifier: Natural Language :: English
Classifier: License :: OSI Approved :: Apache Software License
Classifier: Programming Language :: Python
Classifier: Programming Language :: Python :: 2.7
Classifier: Operating System :: OS Independent
